<?xml version="1.0" encoding="UTF-8"?>
<objects serializationModel="Studio.02.02.00">
	<object class="AudioFile" id="{e48ede52-f5ed-4be1-9e11-ac26f6770c3b}">
		<property name="assetPath">
			<value>Behemoth Melee Attack.wav</value>
		</property>
		<property name="frequencyInKHz">
			<value>48</value>
		</property>
		<property name="channelCount">
			<value>2</value>
		</property>
		<property name="length">
			<value>4.25</value>
		</property>
		<relationship name="masterAssetFolder">
			<destination>{d684575b-bb81-4f25-bc82-5953703e34cf}</destination>
		</relationship>
	</object>
</objects>
